setup.cfg
setup.py
wsgiheaders/__init__.py
wsgiheaders.egg-info/PKG-INFO
wsgiheaders.egg-info/SOURCES.txt
wsgiheaders.egg-info/dependency_links.txt
wsgiheaders.egg-info/entry_points.txt
wsgiheaders.egg-info/not-zip-safe
wsgiheaders.egg-info/requires.txt
wsgiheaders.egg-info/top_level.txt