Metadata-Version: 1.0
Name: wsgiheaders
Version: 0.2
Summary: Adding and replacing response headers
Home-page: http://www.bitbucket.org/aodag/wsgiheaders/
Author: Atsushi Odagiri
Author-email: aodagx@gmail.com
License: MIT License
Platform: UNKNOWN
Classifier: Topic :: Internet :: WWW/HTTP :: WSGI
Classifier: Topic :: Internet :: WWW/HTTP :: WSGI :: Middleware
Classifier: Environment :: Web Environment
Classifier: License :: OSI Approved :: MIT License
Classifier: Development Status :: 3 - Alpha
